{
  "utenti": [
    {
      "username": "giulio",
      "password": "pw",
      "logged": false
    },
    {
      "username": "giovanni",
      "password": "pw2",
      "logged": true
    },
    {
      "username": "marco",
      "password": "pw3",
      "logged": false
    },
    {
      "username": "paolo",
      "password": "umpa",
      "logged": false
    },
    {
      "username": "mirco",
      "password": "pwForte",
      "logged": false
    },
    {
      "username": "novizo",
      "password": "speranza",
      "logged": true
    },
    {
      "username": "ewamke",
      "password": "wsda",
      "logged": false
    },
    {
      "username": "topo",
      "password": "gigio",
      "logged": false
    },
    {
      "username": "gatto",
      "password": "silvestro",
      "logged": false
    }
  ]
}